gingerdj
