Metadata-Version: 2.1
Name: ginger-dj
Version: 6.1.1
Summary: A high-level Python web framework that encourages rapid development and clean, pragmatic design.
Home-page: https://www.gingersociety.org/products/ginger-dj
Author: Ginger Society
Author-email: hello@gingersociety.org
License: BSD-3-Clause
Project-URL: Documentation, https://docs.gingersociety.org/docs/category/ginger-dj
Project-URL: Source, https://github.com/ginger-society/ginger-DJ
Classifier: Development Status :: 2 - Pre-Alpha
Classifier: Environment :: Web Environment
Classifier: Intended Audience :: Developers
Classifier: License :: OSI Approved :: BSD License
Classifier: Operating System :: OS Independent
Classifier: Programming Language :: Python
Classifier: Programming Language :: Python :: 3
Classifier: Programming Language :: Python :: 3 :: Only
Classifier: Programming Language :: Python :: 3.10
Classifier: Programming Language :: Python :: 3.11
Classifier: Programming Language :: Python :: 3.12
Classifier: Topic :: Internet :: WWW/HTTP
Classifier: Topic :: Internet :: WWW/HTTP :: Dynamic Content
Classifier: Topic :: Internet :: WWW/HTTP :: WSGI
Classifier: Topic :: Software Development :: Libraries :: Application Frameworks
Classifier: Topic :: Software Development :: Libraries :: Python Modules
Requires-Python: >=3.10
License-File: LICENSE
License-File: LICENSE.python
Requires-Dist: asgiref>=3.7.0
Requires-Dist: sqlparse>=0.3.1
Requires-Dist: tzdata; sys_platform == "win32"
Provides-Extra: argon2
Requires-Dist: argon2-cffi>=19.1.0; extra == "argon2"
Provides-Extra: bcrypt
Requires-Dist: bcrypt; extra == "bcrypt"
